otp.py
make_otp-1.0.0.dist-info/METADATA
make_otp-1.0.0.dist-info/WHEEL
make_otp-1.0.0.dist-info/top_level.txt
make_otp-1.0.0.dist-info/RECORD
