Metadata-Version: 2.4
Name: make_otp
Version: 1.0.0
Summary: A simple Python library to generate numeric, alphabetic, or alphanumeric OTPs
Author: Muhammed Aman S S
Author-email: aman251104@gmail.com
Classifier: Programming Language :: Python :: 3
Classifier: License :: OSI Approved :: MIT License
Classifier: Operating System :: OS Independent
Classifier: Intended Audience :: Developers
Classifier: Topic :: Security :: Cryptography
Requires-Python: >=3.1
Dynamic: author
Dynamic: author-email
Dynamic: classifier
Dynamic: description
Dynamic: description-content-type
Dynamic: requires-python
Dynamic: summary
